django_admin_multiple_choice_list_filter/__init__.py
django_admin_multiple_choice_list_filter/list_filters.py
django_admin_multiple_choice_list_filter/tests.py
django_admin_multiple_choice_list_filter/templates/django_admin_multiple_choice_list_filter/filter.html
django_admin_multiple_choice_list_filter-0.1.1.dist-info/DESCRIPTION.rst
django_admin_multiple_choice_list_filter-0.1.1.dist-info/METADATA
django_admin_multiple_choice_list_filter-0.1.1.dist-info/RECORD
django_admin_multiple_choice_list_filter-0.1.1.dist-info/WHEEL
django_admin_multiple_choice_list_filter-0.1.1.dist-info/metadata.json
django_admin_multiple_choice_list_filter-0.1.1.dist-info/top_level.txt
