Metadata-Version: 2.0
Name: django-admin-multiple-choice-list-filter
Version: 0.1.1
Summary: A Django app to add a Multiple Choice List Filter to the admin interface.
Home-page: https://github.com/ctxis/django-admin-multiple-choice-list-filter
Author: Patrick Heneghan
Author-email: git@discopatrick.me
License: BSD 2-Clause "Simplified" License
Platform: UNKNOWN
Classifier: Environment :: Web Environment
Classifier: Framework :: Django
Classifier: Framework :: Django :: 2.0
Classifier: Intended Audience :: Developers
Classifier: License :: OSI Approved :: BSD License
Classifier: Operating System :: OS Independent
Classifier: Programming Language :: Python
Classifier: Programming Language :: Python :: 3.5
Classifier: Programming Language :: Python :: 3.6
Classifier: Topic :: Internet :: WWW/HTTP
Classifier: Topic :: Internet :: WWW/HTTP :: Dynamic Content
